syspassclient/__init__.py
syspassclient/api.py
syspassclient/check_type.py
syspassclient/config.py
syspassclient/constants.py
syspassclient/libs.py
syspassclient/object.py
syspassclient/syspassclient.py
syspassclient/api_definition/3.0.yaml
syspassclient/api_definition/3.1.yaml
digdeo_syspass_client-0.6.8.dist-info/LICENSE.txt
digdeo_syspass_client-0.6.8.dist-info/METADATA
digdeo_syspass_client-0.6.8.dist-info/WHEEL
digdeo_syspass_client-0.6.8.dist-info/top_level.txt
digdeo_syspass_client-0.6.8.dist-info/RECORD
