Metadata-Version: 2.1
Name: digdeo-syspass-client
Version: 0.6.8
Summary: DigDeo Syspass Client
Home-page: https://git.digdeo.fr/digdeo-system/FLOSS/digdeo-syspass-client/
Author: DigDeo
Author-email: pierre-henry.muller@digdeo.fr
License: GNU GENERAL PUBLIC LICENSE Version 3
Keywords: DigDeo Syspass Client
Classifier: Development Status :: 5 - Production/Stable
Classifier: Intended Audience :: Developers
Classifier: Intended Audience :: System Administrators
Classifier: License :: OSI Approved :: GNU General Public License v3 or later (GPLv3+)
Classifier: Topic :: Software Development :: Libraries :: Python Modules
Classifier: Topic :: Security
Classifier: Programming Language :: Python
Classifier: Programming Language :: Python :: 2.7
Classifier: Programming Language :: Python :: 3.5
Classifier: Programming Language :: Python :: 3.7
Classifier: Programming Language :: Python :: 3.8
Classifier: Programming Language :: Python :: 3.9
Classifier: Programming Language :: Python :: 3.10
Classifier: Programming Language :: Python :: 3.11
Classifier: Programming Language :: Python :: 3.12
License-File: LICENSE.txt
Requires-Dist: colorama
Requires-Dist: six
Requires-Dist: PyYAML
Requires-Dist: requests
Requires-Dist: urllib3
